crossworlds_modmanager/__about__.py
crossworlds_modmanager/__init__.py
crossworlds_modmanager/main.py
crossworlds_modmanager/register_mime.py
crossworlds_modmanager/unregister_mime.py
crossworlds_modmanager/models/__init__.py
crossworlds_modmanager/models/config.py
crossworlds_modmanager/models/mod.py
crossworlds_modmanager/services/__init__.py
crossworlds_modmanager/services/archive_extractor.py
crossworlds_modmanager/services/mod_downloader.py
crossworlds_modmanager/services/mod_manager.py
crossworlds_modmanager/services/profile_manager.py
crossworlds_modmanager/ui/__init__.py
crossworlds_modmanager/ui/about_tab.py
crossworlds_modmanager/ui/download_tab.py
crossworlds_modmanager/ui/main_window.py
crossworlds_modmanager/ui/mods_tab.py
crossworlds_modmanager/ui/profiles_tab.py
crossworlds_modmanager/ui/settings_tab.py
crossworlds_modmanager/ui/widgets.py
crossworlds_modmanager-0.1.0.data/data/share/crossworlds-modmanager/crossworlds-modmanager.desktop
crossworlds_modmanager-0.1.0.data/data/share/crossworlds-modmanager/register-crosspatch-windows.reg
crossworlds_modmanager-0.1.0.dist-info/METADATA
crossworlds_modmanager-0.1.0.dist-info/WHEEL
crossworlds_modmanager-0.1.0.dist-info/entry_points.txt
crossworlds_modmanager-0.1.0.dist-info/licenses/LICENSE
crossworlds_modmanager-0.1.0.dist-info/RECORD
