Metadata-Version: 2.4
Name: crossworlds-modmanager
Version: 0.1.0
Summary: Manage mods using Crossworlds Mod Manager
Project-URL: Documentation, https://github.com/Yiannis Charalambous/crossworlds-modmanager#readme
Project-URL: Issues, https://github.com/Yiannis Charalambous/crossworlds-modmanager/issues
Project-URL: Source, https://github.com/Yiannis Charalambous/crossworlds-modmanager
Author-email: Yiannis Charalambous <yiannis128@hotmail.com>
License-Expression: AGPL-3.0
License-File: LICENSE
Classifier: Programming Language :: Python :: 3.12
Requires-Python: >=3.12
Requires-Dist: py7zr>=0.20.0
Requires-Dist: pydantic>=2.0.0
Requires-Dist: pyside6>=6.5.0
Requires-Dist: rarfile>=4.0
Requires-Dist: toml>=0.10.2
